frame_picker-0.0.1.dist-info/RECORD
frame_picker-0.0.1.dist-info/WHEEL
frame_picker-0.0.1.dist-info/top_level.txt
frame_picker-0.0.1.dist-info/METADATA
frame_picker/__init__.py
frame_picker/_frame_picker.cpython-38-x86_64-linux-gnu.so
